agentium_sdk/__init__.py
agentium_sdk/_native.cpython-313-darwin.so
agentium_sdk/_native.pyi
agentium_sdk/client.py
agentium_sdk/exceptions.py
agentium_sdk/py.typed
agentium_sdk/types.py
agentium_sdk-0.5.0.dist-info/METADATA
agentium_sdk-0.5.0.dist-info/WHEEL
agentium_sdk-0.5.0.dist-info/RECORD
