Metadata-Version: 2.4
Name: agentium-sdk
Version: 0.5.0
Classifier: Development Status :: 4 - Beta
Classifier: Intended Audience :: Developers
Classifier: License :: OSI Approved :: MIT License
Classifier: Programming Language :: Python :: 3
Classifier: Programming Language :: Python :: 3.10
Classifier: Programming Language :: Python :: 3.11
Classifier: Programming Language :: Python :: 3.12
Classifier: Programming Language :: Python :: 3.13
Classifier: Programming Language :: Rust
Classifier: Topic :: Security :: Cryptography
Requires-Dist: httpx>=0.27
Requires-Dist: pytest>=8.0 ; extra == 'dev'
Requires-Dist: pytest-asyncio>=0.24 ; extra == 'dev'
Requires-Dist: respx>=0.21 ; extra == 'dev'
Requires-Dist: mypy>=1.0 ; extra == 'dev'
Requires-Dist: ruff>=0.8 ; extra == 'dev'
Requires-Dist: mkdocs>=1.6 ; extra == 'docs'
Requires-Dist: mkdocs-material>=9.5 ; extra == 'docs'
Requires-Dist: mkdocstrings[python]>=0.27 ; extra == 'docs'
Provides-Extra: dev
Provides-Extra: docs
Summary: Agentium SDK for Python - DID and Verifiable Credentials
Keywords: did,verifiable-credentials,identity,web3
License: MIT
Requires-Python: >=3.10
Project-URL: Documentation, https://github.com/semiotic-agentium/agentium-sdk
Project-URL: Homepage, https://github.com/semiotic-agentium/agentium-sdk
Project-URL: Repository, https://github.com/semiotic-agentium/agentium-sdk
